[
    {
        "nid": "Swept",
        "name": "Swept",
        "desc": "Struck by windsweep. Avo-10. \nCannot move until next turn.",
        "icon_nid": "All_Icons",
        "icon_index": [
            5,
            47
        ],
        "components": [
            [
                "negative",
                null
            ],
            [
                "avoid",
                -10
            ],
            [
                "cannot_use_items",
                null
            ],
            [
                "lost_on_end_combat",
                [
                    [
                        "LostOnSelf (T/F)",
                        "F",
                        "Lost after self combat (e.g. vulnerary)"
                    ]
                ]
            ]
        ]
    }
]